[
    {
        "id": 1,
        "number": "01",
        "title": "Input taken from users",
        "description": "Excuse Deal say over contain performance from comparison new melancholy themselves.",
        "delay": ""
    },
    {
        "id": 2,
        "number": "02",
        "title": "Activation Function",
        "description": "Excuse Deal say over contain performance from comparison new melancholy themselves.",
        "delay": "200"
    },
    {
        "id": 3,
        "number": "03",
        "title": "Feedforward Process",
        "description": "Excuse Deal say over contain performance from comparison new melancholy themselves.",
        "delay": "400"
    }
]